autodatapre/__init__.py
autodatapre/Pipeline_Generation/Estimate_after_profit.py
autodatapre/Pipeline_Generation/MCTS.py
autodatapre/Pipeline_Generation/MCTS_DATA.py
autodatapre/Pipeline_Generation/MetaFeature.py
autodatapre/Pipeline_Generation/User_Operation.py
autodatapre/Pipeline_Generation/__init__.py
autodatapre/Pipeline_Generation/Estimation_Model/__init__.py
autodatapre/Pipeline_Generation/Estimation_Model/model_CLA.pickle
autodatapre/Pipeline_Generation/Estimation_Model/model_REG.pickle
autodatapre/Search_Space/__init__.py
autodatapre/Search_Space/classifier.py
autodatapre/Search_Space/duplicate_detector.py
autodatapre/Search_Space/encoding.py
autodatapre/Search_Space/feature_selector.py
autodatapre/Search_Space/imputer.py
autodatapre/Search_Space/normalizer.py
autodatapre/Search_Space/outlier_detector.py
autodatapre/Search_Space/regressor.py
autodatapre/datasets/42493.csv
autodatapre/datasets/573.csv
autodatapre/datasets/__init__.py
autodatapre/datasets/dataset/Metafeature.csv
autodatapre/datasets/dataset/MetafeatureREG.csv
autodatapre/datasets/dataset/__init__.py
autodatapre/datasets/dataset/label.csv
autodatapre/datasets/dataset/label_reg.csv
autodatapre-0.1.12.dist-info/METADATA
autodatapre-0.1.12.dist-info/WHEEL
autodatapre-0.1.12.dist-info/top_level.txt
autodatapre-0.1.12.dist-info/RECORD
